<?xml version="1.0"?>
<!DOCTYPE hibernate-mapping PUBLIC "-//Hibernate/Hibernate Mapping DTD 3.0//EN" "http://www.hibernate.org/dtd/hibernate-mapping-3.0.dtd">
<hibernate-mapping auto-import="true" default-access="property" default-cascade="none" default-lazy="true">
	<class abstract="false" name="com.aqm.testing.testDataEntity.PartyEntity" table="PartyEntity">
		<id name="Reference" column="Reference" type="string">
		</id>
		<property name="TestScenario" column="TestScenario" type="string" />
		<property name="RowNumber" column="RowNumber" type="integer" />
		<property name="Action" column="Action" type="string" />
		<property name="StepGroup" column="StepGroup" type="string" />
		<property name="ParentKey" column="ParentKey" type="string" />
		<property name="ChildKey" column="ChildKey" type="string" />
		<property name="ConfigExecute" column="ConfigExecute" type="string" />
		<dynamic-component insert="true" name="customProperties" optimistic-lock="true" unique="false" update="true">
			<property name="LOB" column="LOB" type="string" />
			<property name="Product" column="Product" type="string" />
			<property name="LoginUserReference" column="LoginUserReference" type="string" />
			<property name="DependencyForPartyCode" column="DependencyForPartyCode" type="string" />
			<property name="DependencyForPolicy" column="DependencyForPolicy" type="string" />
			<property name="DependencyForPolicyMember" column="DependencyForPolicyMember" type="string" />
			<property name="DependencyForPolicyBuyer" column="DependencyForPolicyBuyer" type="string" />
			<property name="DependencyForPolicyMemberPremium" column="DependencyForPolicyMemberPremium" type="string" />
			<property name="DependencyForContacts" column="DependencyForContacts" type="string" />
			<property name="DependencyForPartyRoles" column="DependencyForPartyRoles" type="string" />
			<property name="DependencyForPartyRoleMember" column="DependencyForPartyRoleMember" type="string" />
			<property name="DependencyForRelatedParties" column="DependencyForRelatedParties" type="string" />
			<property name="DependencyForPolicyRelation" column="DependencyForPolicyRelation" type="string" />
			<property name="DependencyForFollowup" column="DependencyForFollowup" type="string" />
			<property name="DependencyForPolicyMemberPayments" column="DependencyForPolicyMemberPayments" type="string" />
			<property name="DependencyForSuperUserUserCode" column="DependencyForSuperUserUserCode" type="string" />
			<property name="DependencyForAccountingPartyCode" column="DependencyForAccountingPartyCode" type="string" />
			<property name="DependencyForScrollPartyName" column="DependencyForScrollPartyName" type="string" />
			<property name="DependencyForPolicyPremiumSchedule" column="DependencyForPolicyPremiumSchedule" type="string" />
			<property name="DependencyForClaimPayment" column="DependencyForClaimPayment" type="string" />
			<property name="DependencyForAccountingDistributionTable" column="DependencyForAccountingDistributionTable" type="string" />
			<property name="DependencyForShowVersion" column="DependencyForShowVersion" type="string" />
			<property name="DependencyForClaimTransferToAPEntity" column="DependencyForClaimTransferToAPEntity" type="string" />
			<property name="DependencyForPolicyPremiumCollection" column="DependencyForPolicyPremiumCollection" type="string" />
			<property name="DependencyForMemberName" column="DependencyForMemberName" type="string" />
			<property name="DependencyForParentCode" column="DependencyForParentCode" type="string" />
			<property name="DependencyForClientDetail" column="DependencyForClientDetail" type="string" />
			<property name="ConfigPrimaryInformation" column="ConfigPrimaryInformation" type="boolean" />
			<property name="ConfigSearchIndividual" column="ConfigSearchIndividual" type="boolean" />
			<property name="ConfigIndividual" column="ConfigIndividual" type="boolean" />
			<property name="ConfigSearchOrganization" column="ConfigSearchOrganization" type="boolean" />
			<property name="ConfigOrganization" column="ConfigOrganization" type="boolean" />
			<property name="ConfigSearchPartyCode" column="ConfigSearchPartyCode" type="boolean" />
			<property name="ConfigPartyCode" column="ConfigPartyCode" type="boolean" />
			<property name="PartyCode" column="PartyCode" type="string" />
			<property name="ConfigStakeCode" column="ConfigStakeCode" type="boolean" />
			<property name="StakeCode" column="StakeCode" type="string" />
			<property name="ConfigCompany" column="ConfigCompany" type="boolean" />
			<property name="Company" column="Company" type="string" />
			<property name="ConfigSearchFirstName" column="ConfigSearchFirstName" type="boolean" />
			<property name="ConfigFirstName" column="ConfigFirstName" type="boolean" />
			<property name="FirstName" column="FirstName" type="string" />
			<property name="ConfigMiddleName" column="ConfigMiddleName" type="boolean" />
			<property name="MiddleName" column="MiddleName" type="string" />
			<property name="ConfigSearchLastName" column="ConfigSearchLastName" type="boolean" />
			<property name="ConfigLastName" column="ConfigLastName" type="boolean" />
			<property name="LastName" column="LastName" type="string" />
			<property name="ConfigSearchPartyLinksDropDownList" column="ConfigSearchPartyLinksDropDownList" type="boolean" />
			<property name="SearchPartyLinksDropDown" column="SearchPartyLinksDropDown" type="string" />
			<property name="ConfigSearchPartyLinksTextFeilds" column="ConfigSearchPartyLinksTextFeilds" type="boolean" />
			<property name="SearchPartyLinksTextField" column="SearchPartyLinksTextField" type="string" />
			<property name="ConfigSearchStakeholderFunctionCode" column="ConfigSearchStakeholderFunctionCode" type="boolean" />
			<property name="SearchStakeholderFunctionCode" column="SearchStakeholderFunctionCode" type="string" />
			<property name="ConfigSearchParameterDropDownList" column="ConfigSearchParameterDropDownList" type="boolean" />
			<property name="SearchParameterdropDown" column="SearchParameterdropDown" type="string" />
			<property name="ConfigSearchParameterTextFeild" column="ConfigSearchParameterTextFeild" type="boolean" />
			<property name="SearchParameterTextField" column="SearchParameterTextField" type="string" />
			<property name="ConfigOtherName" column="ConfigOtherName" type="boolean" />
			<property name="OtherName" column="OtherName" type="string" />
			<property name="ConfigTitle" column="ConfigTitle" type="boolean" />
			<property name="Title" column="Title" type="string" />
			<property name="ConfigTitleEdit" column="ConfigTitleEdit" type="boolean" />
			<property name="TitleEdit" column="TitleEdit" type="string" />
			<property name="ConfigSex" column="ConfigSex" type="boolean" />
			<property name="Sex" column="Sex" type="string" />
			<property name="ConfigNationality" column="ConfigNationality" type="boolean" />
			<property name="Nationality" column="Nationality" type="string" />
			<property name="ConfigParentParty" column="ConfigParentParty" type="boolean" />
			<property name="ParentParty" column="ParentParty" type="string" />
			<property name="ConfigParentPartyCodeIndividualEdit" column="ConfigParentPartyCodeIndividualEdit" type="boolean" />
			<property name="ParentPartyCodeIndividualEdit" column="ParentPartyCodeIndividualEdit" type="string" />
			<property name="ConfigStartDate" column="ConfigStartDate" type="boolean" />
			<property name="StartDate" column="StartDate" type="string" />
			<property name="ConfigEndDate" column="ConfigEndDate" type="boolean" />
			<property name="EndDate" column="EndDate" type="string" />
			<property name="ConfigContactType" column="ConfigContactType" type="boolean" />
			<property name="ContactType" column="ContactType" type="string" />
			<property name="ConfigAddress1" column="ConfigAddress1" type="boolean" />
			<property name="Address1" column="Address1" type="string" />
			<property name="ConfigAddress2" column="ConfigAddress2" type="boolean" />
			<property name="Address2" column="Address2" type="string" />
			<property name="ConfigAddressAlongWithCityName" column="ConfigAddressAlongWithCityName" type="boolean" />
			<property name="AddressAlongWithCityName" column="AddressAlongWithCityName" type="string" />
			<property name="ConfigCityCode" column="ConfigCityCode" type="boolean" />
			<property name="CityCode" column="CityCode" type="string" />
			<property name="ConfigCityName" column="ConfigCityName" type="boolean" />
			<property name="CityName" column="CityName" type="string" />
			<property name="ConfigStateCode" column="ConfigStateCode" type="boolean" />
			<property name="StateCode" column="StateCode" type="string" />
			<property name="ConfigStateName" column="ConfigStateName" type="boolean" />
			<property name="StateName" column="StateName" type="string" />
			<property name="ConfigCountryCode" column="ConfigCountryCode" type="boolean" />
			<property name="CountryCode" column="CountryCode" type="string" />
			<property name="ConfigCountryName" column="ConfigCountryName" type="boolean" />
			<property name="CountryName" column="CountryName" type="string" />
			<property name="ConfigPinCode" column="ConfigPinCode" type="boolean" />
			<property name="PinCode" column="PinCode" type="string" />
			<property name="ConfigTelephoneNumberHome" column="ConfigTelephoneNumberHome" type="boolean" />
			<property name="TelephoneNumberHome" column="TelephoneNumberHome" type="string" />
			<property name="ConfigTelephoneNumberOffice" column="ConfigTelephoneNumberOffice" type="boolean" />
			<property name="TelephoneNumberOffice" column="TelephoneNumberOffice" type="string" />
			<property name="ConfigMobileNo" column="ConfigMobileNo" type="boolean" />
			<property name="MobileNo" column="MobileNo" type="string" />
			<property name="ConfigFaxNumberHome" column="ConfigFaxNumberHome" type="boolean" />
			<property name="FaxNumberHome" column="FaxNumberHome" type="string" />
			<property name="ConfigFaxNumberOffice" column="ConfigFaxNumberOffice" type="boolean" />
			<property name="FaxNumberOffice" column="FaxNumberOffice" type="string" />
			<property name="ConfigEmailIdHome" column="ConfigEmailIdHome" type="boolean" />
			<property name="EmailIdHome" column="EmailIdHome" type="string" />
			<property name="ConfigEmailIdOffice" column="ConfigEmailIdOffice" type="boolean" />
			<property name="EmailIdOffice" column="EmailIdOffice" type="string" />
			<property name="ConfigBlackListIndicator" column="ConfigBlackListIndicator" type="boolean" />
			<property name="BlackListIndicator" column="BlackListIndicator" type="string" />
			<property name="ConfigPartyOccupation" column="ConfigPartyOccupation" type="boolean" />
			<property name="PartyOccupation" column="PartyOccupation" type="string" />
			<property name="ConfigPanNumber" column="ConfigPanNumber" type="boolean" />
			<property name="PanNumber" column="PanNumber" type="string" />
			<property name="ConfigTanNumber" column="ConfigTanNumber" type="boolean" />
			<property name="TanNumber" column="TanNumber" type="string" />
			<property name="ConfigTDSVendor" column="ConfigTDSVendor" type="boolean" />
			<property name="TDSVendor" column="TDSVendor" type="string" />
			<property name="ConfigSectionCode" column="ConfigSectionCode" type="boolean" />
			<property name="SectionCode" column="SectionCode" type="string" />
			<property name="ConfigWardNo" column="ConfigWardNo" type="boolean" />
			<property name="WardNo" column="WardNo" type="string" />
			<property name="ConfigContactPerson" column="ConfigContactPerson" type="boolean" />
			<property name="ContactPerson" column="ContactPerson" type="string" />
			<property name="ConfigSector" column="ConfigSector" type="boolean" />
			<property name="Sector" column="Sector" type="string" />
			<property name="ConfigClientType" column="ConfigClientType" type="boolean" />
			<property name="ClientType" column="ClientType" type="string" />
			<property name="ConfigProspectId" column="ConfigProspectId" type="boolean" />
			<property name="ProspectId" column="ProspectId" type="string" />
			<property name="ConfigDateOfBirth" column="ConfigDateOfBirth" type="boolean" />
			<property name="DateOfBirth" column="DateOfBirth" type="string" />
			<property name="ConfigBusinessType" column="ConfigBusinessType" type="boolean" />
			<property name="BusinessType" column="BusinessType" type="string" />
			<property name="ConfigManualPartyCode" column="ConfigManualPartyCode" type="boolean" />
			<property name="ManualPartyCode" column="ManualPartyCode" type="string" />
			<property name="ConfigCoInsuranceApplicable" column="ConfigCoInsuranceApplicable" type="boolean" />
			<property name="CoInsuranceApplicable" column="CoInsuranceApplicable" type="string" />
			<property name="ConfigPartyBankCode" column="ConfigPartyBankCode" type="boolean" />
			<property name="PartyBankCode" column="PartyBankCode" type="string" />
			<property name="ConfigPartyBankAccountNumber" column="ConfigPartyBankAccountNumber" type="boolean" />
			<property name="PartyBankAccountNumber" column="PartyBankAccountNumber" type="string" />
			<property name="ConfigReTypePartyBankAccountNumber" column="ConfigReTypePartyBankAccountNumber" type="boolean" />
			<property name="ReTypePartyBankAccountNumber" column="ReTypePartyBankAccountNumber" type="string" />
			<property name="ConfigPartyPaymentMethod" column="ConfigPartyPaymentMethod" type="boolean" />
			<property name="PartyPaymentMethod" column="PartyPaymentMethod" type="string" />
			<property name="ConfigPartyAccountType" column="ConfigPartyAccountType" type="boolean" />
			<property name="PartyAccountType" column="PartyAccountType" type="string" />
			<property name="ConfigNameOfTheCountry" column="ConfigNameOfTheCountry" type="boolean" />
			<property name="NameOfTheCountry" column="NameOfTheCountry" type="string" />
			<property name="ConfigZipCode" column="ConfigZipCode" type="boolean" />
			<property name="ZipCode" column="ZipCode" type="string" />
			<property name="ConfigAADHARNo" column="ConfigAADHARNo" type="boolean" />
			<property name="AADHARNo" column="AADHARNo" type="string" />
			<property name="ConfigRelationshipWithRegisteredUser" column="ConfigRelationshipWithRegisteredUser" type="boolean" />
			<property name="RelationshipWithRegisteredUser" column="RelationshipWithRegisteredUser" type="string" />
			<property name="ConfigEInsuranceAccountNo" column="ConfigEInsuranceAccountNo" type="boolean" />
			<property name="EInsuranceAccountNo" column="EInsuranceAccountNo" type="string" />
			<property name="ConfigDoYouWantToAddMemberStake" column="ConfigDoYouWantToAddMemberStake" type="boolean" />
			<property name="DoYouWantToAddMemberStake" column="DoYouWantToAddMemberStake" type="string" />
			<property name="ConfigBMBAccountNumber" column="ConfigBMBAccountNumber" type="boolean" />
			<property name="BMBAccountNumber" column="BMBAccountNumber" type="string" />
			<property name="ConfigClaimServicingOfficeCode" column="ConfigClaimServicingOfficeCode" type="boolean" />
			<property name="ClaimServicingOfficeCode" column="ClaimServicingOfficeCode" type="string" />
			<property name="ConfigSearchBusinessName" column="ConfigSearchBusinessName" type="boolean" />
			<property name="SearchBusinessName" column="SearchBusinessName" type="string" />
			<property name="ConfigBusinessName" column="ConfigBusinessName" type="boolean" />
			<property name="BusinessName" column="BusinessName" type="string" />
			<property name="ConfigProposerName" column="ConfigProposerName" type="boolean" />
			<property name="ProposerName" column="ProposerName" type="string" />
			<property name="ConfigRegistrationNo" column="ConfigRegistrationNo" type="boolean" />
			<property name="RegistrationNo" column="RegistrationNo" type="string" />
			<property name="ConfigRegistrationDate" column="ConfigRegistrationDate" type="boolean" />
			<property name="RegistrationDate" column="RegistrationDate" type="string" />
			<property name="ConfigTypeOfOrganization" column="ConfigTypeOfOrganization" type="boolean" />
			<property name="TypeOfOrganization" column="TypeOfOrganization" type="string" />
			<property name="ConfigParentCode" column="ConfigParentCode" type="boolean" />
			<property name="ParentCode" column="ParentCode" type="string" />
			<property name="ConfigParentCodeOrganizationEdit" column="ConfigParentCodeOrganizationEdit" type="boolean" />
			<property name="ParentCodeOrganizationEdit" column="ParentCodeOrganizationEdit" type="string" />
			<property name="ConfigBusinessAddress1" column="ConfigBusinessAddress1" type="boolean" />
			<property name="BusinessAddress1" column="BusinessAddress1" type="string" />
			<property name="ConfigBusinessAddress2" column="ConfigBusinessAddress2" type="boolean" />
			<property name="BusinessAddress2" column="BusinessAddress2" type="string" />
			<property name="ConfigBusinessAddressAlongWithCityName" column="ConfigBusinessAddressAlongWithCityName" type="boolean" />
			<property name="BusinessAddressAlongWithCityName" column="BusinessAddressAlongWithCityName" type="string" />
			<property name="ConfigBusinessTelNumOff" column="ConfigBusinessTelNumOff" type="boolean" />
			<property name="BusinessTelNumOff" column="BusinessTelNumOff" type="string" />
			<property name="ConfigBusinessTelNumExtn" column="ConfigBusinessTelNumExtn" type="boolean" />
			<property name="BusinessTelNumExtn" column="BusinessTelNumExtn" type="string" />
			<property name="ConfigFaxNo1" column="ConfigFaxNo1" type="boolean" />
			<property name="FaxNo1" column="FaxNo1" type="string" />
			<property name="ConfigFaxNo2" column="ConfigFaxNo2" type="boolean" />
			<property name="FaxNo2" column="FaxNo2" type="string" />
			<property name="ConfigEmailId1" column="ConfigEmailId1" type="boolean" />
			<property name="EmailId1" column="EmailId1" type="string" />
			<property name="ConfigEmailId2" column="ConfigEmailId2" type="boolean" />
			<property name="EmailId2" column="EmailId2" type="string" />
			<property name="ConfigPaidUpCapital" column="ConfigPaidUpCapital" type="boolean" />
			<property name="PaidUpCapital" column="PaidUpCapital" type="string" />
			<property name="ConfigAddressForCorrespondence" column="ConfigAddressForCorrespondence" type="boolean" />
			<property name="AddressForCorrespondence" column="AddressForCorrespondence" type="string" />
			<property name="ConfigSaveBtn" column="ConfigSaveBtn" type="boolean" />
			<property name="ConfigEditButton" column="ConfigEditButton" type="boolean" />
			<property name="ConfigDeleteButton" column="ConfigDeleteButton" type="boolean" />
			<property name="ConfigShowVersionButton" column="ConfigShowVersionButton" type="boolean" />
			<property name="ConfigBackButton" column="ConfigBackButton" type="boolean" />
			<property name="ConfigPolicyListButton" column="ConfigPolicyListButton" type="boolean" />
			<property name="ConfigClaimListButton" column="ConfigClaimListButton" type="boolean" />
			<property name="ConfigCompleteEditButton" column="ConfigCompleteEditButton" type="boolean" />
			<property name="ConfigClearButton" column="ConfigClearButton" type="boolean" />
			<property name="ConfigForReason" column="ConfigForReason" type="boolean" />
			<property name="ReasonTextField" column="ReasonTextField" type="string" />
			<property name="ConfigDateofReason" column="ConfigDateofReason" type="boolean" />
			<property name="DateofReason" column="DateofReason" type="string" />
			<property name="ConfigSaveForReasonPage" column="ConfigSaveForReasonPage" type="boolean" />
			<property name="ConfigParty" column="ConfigParty" type="boolean" />
			<property name="ConfigPartyRoles" column="ConfigPartyRoles" type="boolean" />
			<property name="ConfigContacts" column="ConfigContacts" type="boolean" />
			<property name="ConfigRelatedParties" column="ConfigRelatedParties" type="boolean" />
			<property name="ConfigFollowup" column="ConfigFollowup" type="boolean" />
			<property name="ConfigHierarchy" column="ConfigHierarchy" type="boolean" />
			<property name="ConfigCurrentTime" column="ConfigCurrentTime" type="boolean" />
			<property name="CurrentTime" column="CurrentTime" type="string" />
			<property name="ConfigTypeOfOfficer" column="ConfigTypeOfOfficer" type="boolean" />
			<property name="TypeOfOfficer" column="TypeOfOfficer" type="string" />
			<property name="ConfigUserId" column="ConfigUserId" type="boolean" />
			<property name="UserId" column="UserId" type="string" />
			<property name="ConfigRole" column="ConfigRole" type="boolean" />
			<property name="Role" column="Role" type="string" />
			<property name="ConfigEducationalQualification" column="ConfigEducationalQualification" type="boolean" />
			<property name="EducationalQualification" column="EducationalQualification" type="string" />
			<property name="ConfigProfessionalQualification" column="ConfigProfessionalQualification" type="boolean" />
			<property name="ProfessionalQualification" column="ProfessionalQualification" type="string" />
			<property name="ConfigPassportSizePhotographSubmitted" column="ConfigPassportSizePhotographSubmitted" type="boolean" />
			<property name="PassportSizePhotographSubmitted" column="PassportSizePhotographSubmitted" type="string" />
			<property name="ConfigAgeProofSubmitted" column="ConfigAgeProofSubmitted" type="boolean" />
			<property name="AgeProofSubmitted" column="AgeProofSubmitted" type="string" />
			<property name="ConfigPANCardcopySubmitted" column="ConfigPANCardcopySubmitted" type="boolean" />
			<property name="PANCardcopySubmitted" column="PANCardcopySubmitted" type="string" />
			<property name="ConfigRersidentialAddressProofSubmitted" column="ConfigRersidentialAddressProofSubmitted" type="boolean" />
			<property name="RersidentialAddressProofSubmitted" column="RersidentialAddressProofSubmitted" type="string" />
			<property name="ConfigQualificationProofBasicSubmitted" column="ConfigQualificationProofBasicSubmitted" type="boolean" />
			<property name="QualificationProofBasicSubmitted" column="QualificationProofBasicSubmitted" type="string" />
			<property name="ConfigProfessionalQualificationProofSubmitted" column="ConfigProfessionalQualificationProofSubmitted" type="boolean" />
			<property name="ProfessionalQualificationProofSubmitted" column="ProfessionalQualificationProofSubmitted" type="string" />
			<property name="ConfigExaminationPassCertificateAgentExamSubmitted" column="ConfigExaminationPassCertificateAgentExamSubmitted" type="boolean" />
			<property name="ExaminationPassCertificateAgentExamSubmitted" column="ExaminationPassCertificateAgentExamSubmitted" type="string" />
			<property name="ConfigCessationCertificateFromOtherCompanySubmitted" column="ConfigCessationCertificateFromOtherCompanySubmitted" type="boolean" />
			<property name="CessationCertificateFromOtherCompanySubmitted" column="CessationCertificateFromOtherCompanySubmitted" type="string" />
			<property name="ConfigUndertakingDocumentSubmitted" column="ConfigUndertakingDocumentSubmitted" type="boolean" />
			<property name="UndertakingDocumentSubmitted" column="UndertakingDocumentSubmitted" type="string" />
			<property name="ConfigTrainingExperienceCertificateSubmitted" column="ConfigTrainingExperienceCertificateSubmitted" type="boolean" />
			<property name="TrainingExperienceCertificateSubmitted" column="TrainingExperienceCertificateSubmitted" type="string" />
			<property name="ConfigOriginalIRDAILicenseIDCardSubmitted" column="ConfigOriginalIRDAILicenseIDCardSubmitted" type="boolean" />
			<property name="OriginalIRDAILicenseIDCardSubmitted" column="OriginalIRDAILicenseIDCardSubmitted" type="string" />
			<property name="ConfigNominatedForExam" column="ConfigNominatedForExam" type="boolean" />
			<property name="ConfigQualifiedForExam" column="ConfigQualifiedForExam" type="boolean" />
			<property name="ConfigPassedForExam" column="ConfigPassedForExam" type="boolean" />
			<property name="ConfigApproveOrActivateAgent" column="ConfigApproveOrActivateAgent" type="boolean" />
			<property name="ConfigFatherHusbandName" column="ConfigFatherHusbandName" type="boolean" />
			<property name="FatherHusbandName" column="FatherHusbandName" type="string" />
			<property name="ConfigIMFLicenseNoIMF" column="ConfigIMFLicenseNoIMF" type="boolean" />
			<property name="IMFLicenseNoIMF" column="IMFLicenseNoIMF" type="string" />
			<property name="ConfigLicenseIssueDateIMF" column="ConfigLicenseIssueDateIMF" type="boolean" />
			<property name="LicenseIssueDateIMF" column="LicenseIssueDateIMF" type="string" />
			<property name="ConfigLicenseExpiryDateIMF" column="ConfigLicenseExpiryDateIMF" type="boolean" />
			<property name="LicenseExpiryDateIMF" column="LicenseExpiryDateIMF" type="string" />
			<property name="ConfigBranchNameIMF" column="ConfigBranchNameIMF" type="boolean" />
			<property name="BranchNameIMF" column="BranchNameIMF" type="string" />
			<property name="ConfigBranchTypeIMF" column="ConfigBranchTypeIMF" type="boolean" />
			<property name="BranchTypeIMF" column="BranchTypeIMF" type="string" />
			<property name="ConfigManualPartyCodeIMF" column="ConfigManualPartyCodeIMF" type="boolean" />
			<property name="ManualPartyCodeIMF" column="ManualPartyCodeIMF" type="string" />
			<property name="ConfigAgentLicenseNo" column="ConfigAgentLicenseNo" type="boolean" />
			<property name="AgentLicenseNo" column="AgentLicenseNo" type="string" />
			<property name="ConfigDateOfBirthPerspectiveAgent" column="ConfigDateOfBirthPerspectiveAgent" type="boolean" />
			<property name="DateOfBirthPerspectiveAgent" column="DateOfBirthPerspectiveAgent" type="string" />
			<property name="ConfigDeptSurveyor" column="ConfigDeptSurveyor" type="boolean" />
			<property name="DeptSurveyor" column="DeptSurveyor" type="string" />
			<property name="ConfigIIISLAMembershipNumber" column="ConfigIIISLAMembershipNumber" type="boolean" />
			<property name="IIISLAMembershipNumber" column="IIISLAMembershipNumber" type="string" />
			<property name="ConfigSurveyorLicenseNumber" column="ConfigSurveyorLicenseNumber" type="boolean" />
			<property name="ConfigSurveyorLicenseStartDate" column="ConfigSurveyorLicenseStartDate" type="boolean" />
			<property name="SurveyorLicenseStartDate" column="SurveyorLicenseStartDate" type="string" />
			<property name="ConfigSurveyorLicenseExpiryDate" column="ConfigSurveyorLicenseExpiryDate" type="boolean" />
			<property name="SurveyorLicenseExpiryDate" column="SurveyorLicenseExpiryDate" type="string" />
			<property name="ConfigSurveyorName" column="ConfigSurveyorName" type="boolean" />
			<property name="SurveyorName" column="SurveyorName" type="string" />
			<property name="ConfigKYCIdentificationNumber" column="ConfigKYCIdentificationNumber" type="boolean" />
			<property name="KYCIdentificationNumber" column="KYCIdentificationNumber" type="string" />
			<property name="ConfigAADHARAuthenticationStatus" column="ConfigAADHARAuthenticationStatus" type="boolean" />
			<property name="AADHARAuthenticationStatus" column="AADHARAuthenticationStatus" type="string" />
		</dynamic-component>
	</class>
</hibernate-mapping>
